fintuna/__init__.py
fintuna/finstudy.py
fintuna/run.py
fintuna/data/.DS_Store
fintuna/data/btcpairs_with_social_sentiment.h5
fintuna/data/btcpairs_with_social_sentiment.json
fintuna/data/crypto_features.h5
fintuna/data/data.py
fintuna/data/__pycache__/data.cpython-38.pyc
fintuna/ensemble/BaseEnsemble.py
fintuna/ensemble/IndividualEnsemble.py
fintuna/ensemble/__init__.py
fintuna/model/LongOnly.py
fintuna/model/ModelBase.py
fintuna/model/Pumps.py
fintuna/model/__init__.py
fintuna/sink/LogSink.py
fintuna/sink/__init__.py
fintuna/utils/__init__.py
fintuna/utils/utils.py
fintuna-0.1.5.dist-info/METADATA
fintuna-0.1.5.dist-info/WHEEL
fintuna-0.1.5.dist-info/top_level.txt
fintuna-0.1.5.dist-info/RECORD
