Metadata-Version: 2.1
Name: fintuna
Version: 0.1.5
Summary: Parameter optimization for finance
Author-email: Cortecs <office@cortecs.ai>
Project-URL: Homepage, https://github.com/markoarnauto/fintuna
Project-URL: Bug Tracker, https://github.com/markoarnauto/fintuna/issues
Classifier: Programming Language :: Python :: 3
Classifier: License :: OSI Approved :: GNU General Public License v3 (GPLv3)
Classifier: Operating System :: OS Independent
Requires-Python: >=3.7
Requires-Dist: pandas (~=1.2.3)
Requires-Dist: numpy (~=1.20.0)
Requires-Dist: scikit-learn (==0.24.1)
Requires-Dist: APScheduler (==3.7.0)
Requires-Dist: lightgbm (==3.2.1)
Requires-Dist: QuantStats (==0.0.46)
Requires-Dist: matplotlib (~=3.4.3)
Requires-Dist: optuna (~=3.0.0)
Requires-Dist: tables (~=3.7.0)
Provides-Extra: dev
Requires-Dist: shap (~=0.40.0) ; extra == 'dev'
Requires-Dist: python-binance (~=1.0.0) ; extra == 'dev'
Requires-Dist: sphinx (~=5.2.0) ; extra == 'dev'
Requires-Dist: sphinx-rtd-theme (~=1.0.0) ; extra == 'dev'
Requires-Dist: myst-nb (~=0.17.1) ; extra == 'dev'
Requires-Dist: sphinx-toolbox (~=3.2.0) ; extra == 'dev'
